_copium.pth
copium.cpython-314-aarch64-linux-gnu.so
copium/__about__.pyi
copium/__init__.pyi
copium/extra.pyi
copium/patch.pyi
copium/py.typed
copium-0.1.0a1.dev143.dist-info/METADATA
copium-0.1.0a1.dev143.dist-info/WHEEL
copium-0.1.0a1.dev143.dist-info/top_level.txt
copium-0.1.0a1.dev143.dist-info/RECORD
copium-0.1.0a1.dev143.dist-info/licenses/LICENSE
