Metadata-Version: 2.4
Name: copium
Version: 0.1.0a1.dev143
Summary: Fast drop-in replacement for copy.deepcopy()
Author-email: "Arseny Boykov (Bobronium)" <hi@bobronium.me>
License-Expression: MIT
Project-URL: Homepage, https://github.com/Bobronium/copium
Project-URL: Source, https://github.com/Bobronium/copium
Project-URL: Issues, https://github.com/Bobronium/copium/issues
Classifier: Programming Language :: Python :: 3
Classifier: Programming Language :: Python :: 3 :: Only
Classifier: Programming Language :: Python :: 3.10
Classifier: Programming Language :: Python :: 3.11
Classifier: Programming Language :: Python :: 3.12
Classifier: Programming Language :: Python :: 3.13
Classifier: Programming Language :: Python :: 3.14
Classifier: Development Status :: 3 - Alpha
Classifier: Intended Audience :: Developers
Classifier: Topic :: Software Development :: Libraries
Requires-Python: >=3.10
License-File: LICENSE
Provides-Extra: autopatch
Requires-Dist: copium-autopatch==0.1.0; extra == "autopatch"
Provides-Extra: dev
Requires-Dist: copium[lint]; extra == "dev"
Requires-Dist: copium[typecheck]; extra == "dev"
Requires-Dist: copium[test]; extra == "dev"
Requires-Dist: copium[docs]; extra == "dev"
Provides-Extra: lint
Requires-Dist: ruff>=0.5; extra == "lint"
Provides-Extra: typecheck
Requires-Dist: mypy>=1.10; extra == "typecheck"
Requires-Dist: pyright>=1.1.400; extra == "typecheck"
Requires-Dist: zuban>=0.2.0; extra == "typecheck"
Requires-Dist: pytest; extra == "typecheck"
Provides-Extra: test
Requires-Dist: pytest>=8; extra == "test"
Requires-Dist: pytest-assert-type>=0.1.5; extra == "test"
Requires-Dist: indifference>=0.1.0; extra == "test"
Requires-Dist: typing-extensions; python_version < "3.12" and extra == "test"
Requires-Dist: datamodelzoo; extra == "test"
Requires-Dist: pytest-codspeed>=4.2.0; extra == "test"
Requires-Dist: pytest-test-groups>=1.2.1; extra == "test"
Requires-Dist: psutil>=5.9.0; extra == "test"
Requires-Dist: pytest-random-order>=1.2.0; extra == "test"
Provides-Extra: docs
Requires-Dist: mkdocs-material; extra == "docs"
Requires-Dist: mkdocstrings[python]; extra == "docs"
Requires-Dist: mkdocs-autorefs; extra == "docs"
Requires-Dist: mkdocs-section-index; extra == "docs"
Provides-Extra: benchmark
Requires-Dist: tyro>=0.9.33; extra == "benchmark"
Requires-Dist: pyperf>=2.9.0; extra == "benchmark"
Requires-Dist: ipython>=8.37.0; extra == "benchmark"
Requires-Dist: datamodelzoo; extra == "benchmark"
Requires-Dist: svg-py>=1.10.0; extra == "benchmark"
Requires-Dist: nbconvert>=7.17.0; extra == "benchmark"
Requires-Dist: jupytext>=1.19.1; extra == "benchmark"
Requires-Dist: ipykernel>=7.1.0; extra == "benchmark"
Provides-Extra: build
Requires-Dist: build>=1.3.0; extra == "build"
Requires-Dist: cibuildwheel>=2.23.3; extra == "build"
Requires-Dist: pip>=25.3; extra == "build"
Requires-Dist: setuptools>=80.9.0; extra == "build"
Requires-Dist: setuptools-scm>=9.2.2; extra == "build"
Requires-Dist: wheel>=0.45.1; extra == "build"
Dynamic: license-file
